CHANGES.rst
MANIFEST.in
README.rst
setup.cfg
setup.py
flekky/__init__.py
flekky/flekky.py
flekky/init
flekky.egg-info/PKG-INFO
flekky.egg-info/SOURCES.txt
flekky.egg-info/dependency_links.txt
flekky.egg-info/entry_points.txt
flekky.egg-info/requires.txt
flekky.egg-info/top_level.txt
flekky/init/pages
flekky/init/static
flekky/init/templates
flekky/init/pages/index.md
flekky/init/static/css/style.css
flekky/init/templates/base.html
flekky/init/templates/layout/default.html
test/__init__.py
test/test_flekky.py
test/test_headings.py